napari_pystackreg/__init__.py
napari_pystackreg/_sample_data.py
napari_pystackreg/_util.py
napari_pystackreg/_widget.py
napari_pystackreg/napari.yaml
napari_pystackreg/_tests/__init__.py
napari_pystackreg/_tests/test_sample_data.py
napari_pystackreg/_tests/test_widget.py
napari_pystackreg-0.1.4.dist-info/LICENSE
napari_pystackreg-0.1.4.dist-info/METADATA
napari_pystackreg-0.1.4.dist-info/WHEEL
napari_pystackreg-0.1.4.dist-info/entry_points.txt
napari_pystackreg-0.1.4.dist-info/top_level.txt
napari_pystackreg-0.1.4.dist-info/RECORD
