Metadata-Version: 2.1
Name: napari-pystackreg
Version: 0.1.4
Summary: Robust image registration for napari
Home-page: https://github.com/glichtner/napari-pystackreg
Author: Gregor Lichtner
Author-email: gregor.lichtner@med.uni-greifswald.de
License: Apache-2.0
Project-URL: Bug Tracker, https://github.com/glichtner/napari-pystackreg/issues
Project-URL: Documentation, https://github.com/glichtner/napari-pystackreg#README.md
Project-URL: Source Code, https://github.com/glichtner/napari-pystackreg
Project-URL: User Support, https://github.com/glichtner/napari-pystackreg/issues
Classifier: Development Status :: 4 - Beta
Classifier: Framework :: napari
Classifier: Intended Audience :: Developers
Classifier: License :: OSI Approved :: Apache Software License
Classifier: Operating System :: OS Independent
Classifier: Programming Language :: Python
Classifier: Programming Language :: Python :: 3
Classifier: Programming Language :: Python :: 3 :: Only
Classifier: Programming Language :: Python :: 3.8
Classifier: Programming Language :: Python :: 3.9
Classifier: Programming Language :: Python :: 3.10
Classifier: Topic :: Software Development :: Testing
Requires-Python: >=3.8
License-File: LICENSE
Requires-Dist: magicgui
Requires-Dist: numpy
Requires-Dist: pystackreg (>=0.2.6)
Requires-Dist: qtpy
Provides-Extra: testing
Requires-Dist: napari ; extra == 'testing'
Requires-Dist: pyqt5 ; extra == 'testing'
Requires-Dist: pytest ; extra == 'testing'
Requires-Dist: pytest-cov ; extra == 'testing'
Requires-Dist: pytest-qt ; extra == 'testing'
Requires-Dist: tox ; extra == 'testing'
